antelopy/__init__.py
antelopy/cache/__init__.py
antelopy/cache/abicache.py
antelopy/cache/chain_interface.py
antelopy/exceptions/__init__.py
antelopy/exceptions/exceptions.py
antelopy/serializers/__init__.py
antelopy/serializers/assets.py
antelopy/serializers/keys.py
antelopy/serializers/names.py
antelopy/serializers/time_points.py
antelopy/serializers/varints.py
antelopy/types/__init__.py
antelopy/types/abi.py
antelopy/types/serializables.py
antelopy/types/serializers.py
antelopy/types/transaction.py
antelopy/types/types.py
antelopy/utils/__init__.py
antelopy/utils/base58.py
antelopy-0.2.0.dist-info/LICENSE
antelopy-0.2.0.dist-info/METADATA
antelopy-0.2.0.dist-info/WHEEL
antelopy-0.2.0.dist-info/RECORD
