Metadata-Version: 2.1
Name: antelopy
Version: 0.2.0
Summary: Python helper for Antelope transaction serialization
Home-page: https://antelopy.stuckatsixpm.com
License: MIT
Author: Jake Hattwell
Author-email: stuck@sixpm.dev
Requires-Python: >=3.8,<4.0
Classifier: License :: OSI Approved :: MIT License
Classifier: Programming Language :: Python :: 3
Classifier: Programming Language :: Python :: 3.8
Classifier: Programming Language :: Python :: 3.9
Classifier: Programming Language :: Python :: 3.10
Classifier: Programming Language :: Python :: 3.11
Classifier: Programming Language :: Python :: 3.12
Requires-Dist: pydantic (>=2.4.2,<3.0.0)
Requires-Dist: requests (>=2.31.0,<3.0.0)
Project-URL: Documentation, https://antelopy.stuckatsixpm.com
Project-URL: Repository, https://github.com/stuckatsixpm/antelopy
